README.md
setup.cfg
setup.py
distributions_tomsloni/Binomialdistribution.py
distributions_tomsloni/Gaussiandistribution.py
distributions_tomsloni/Generaldistribution.py
distributions_tomsloni/__init__.py
distributions_tomsloni.egg-info/PKG-INFO
distributions_tomsloni.egg-info/SOURCES.txt
distributions_tomsloni.egg-info/dependency_links.txt
distributions_tomsloni.egg-info/not-zip-safe
distributions_tomsloni.egg-info/top_level.txt